{
  "buildCommand" : {
    "command" : "build",
    "skipDependencies" : false,
    "style" : "buildAndRun"
  },
  "configuredTargets" : [
    {
      "guid" : "e4207be4598f553d3c236b7b43034b7b6e0edb92fe2e923cf93c896a460c37d7"
    }
  ],
  "containerPath" : "/Users/mauriello/Dev/caliber-macos/Caliber.xcodeproj",
  "continueBuildingAfterErrors" : false,
  "dependencyScope" : "workspace",
  "enableIndexBuildArena" : false,
  "hideShellScriptEnvironment" : false,
  "parameters" : {
    "action" : "build",
    "overrides" : {
      "commandLine" : {
        "table" : {
          "CODE_SIGN_IDENTITY" : "-",
          "CODE_SIGNING_ALLOWED" : "NO",
          "CODE_SIGNING_REQUIRED" : "NO"
        }
      },
      "synthesized" : {
        "table" : {
          "ACTION" : "build",
          "ENABLE_PREVIEWS" : "NO",
          "ENABLE_XOJIT_PREVIEWS" : "NO"
        }
      }
    }
  },
  "showNonLoggedProgress" : true,
  "useDryRun" : false,
  "useImplicitDependencies" : false,
  "useLegacyBuildLocations" : false,
  "useParallelTargets" : true
}